{
  "name": "Part to Terrain - Production",
  "tree": {
    "$className": "DataModel",

    "ReplicatedStorage" : {
      "$className": "ReplicatedStorage",
      "PartToTerrain": {
        "$path": "src",

        "Packages": {
          "$className": "Folder",
          "Roact": {
            "$path": "packages/Roact/src"
          },
          "BasicState": {
            "$path": "packages/BasicState/src"
          }
        }
      }

    }
  },

  "globIgnorePaths": [
    "**.spec.lua",
    "**.story.lua",
    "packages/Roact/*.spec"
  ]
}
